[
    {
        "firstName": "Abu",
        "lastName": "Russel",
        "balance": 23991.982,
        "age": "23",
        "dob": "2025-04-09",
        "maritalStatus": "Single",
        "bloodGroup": "A-",
        "country": "Bangladesh",
        "division": "Rajshahi",
        "district": "Bogura",
        "email": "xyz@",
        "password": "scrypt:32768:8:1$uwbmsUCxHZUHyuMQ$f75d37088bc209608b669ebb196086a0d68ca905a619235eb731a9d6a5ea144a97e56d03a5f53104d08318e2507d1553044a70cd50d6e183ba66408c57ecbe6a",
        "phone": "01303501932",
        "joiningDate": "26 April 2025",
        "id": "253JWHKCKFKJ"
    },
    {
        "firstName": "Abu",
        "lastName": "Russel",
        "balance": 2503.7999999999993,
        "age": "23",
        "dob": "2025-05-16",
        "maritalStatus": "Single",
        "bloodGroup": "A-",
        "country": "Bangladesh",
        "division": "Rajshahi",
        "district": "Bogura",
        "email": "aburussel87@gmail.com",
        "password": "scrypt:32768:8:1$4PQEZQr9pxjRF8XA$1a48506f2921ff52549c46a6f041eabee666c2542aa801656c034ac636657eb3f0eb56977b10f72fdbf585737995fd5e702d2314a93daa0522f6212bcb56c63d",
        "phone": "01303501932",
        "joiningDate": "02 May 2025",
        "id": "25MHRI2HUPSM"
    }
]